django_easy_tenants-0.9.5.dist-info/licenses/AUTHORS
django_easy_tenants-0.9.5.dist-info/licenses/LICENSE
easy_tenants/__init__.py
easy_tenants/apps.py
easy_tenants/exceptions.py
easy_tenants/models.py
easy_tenants/storage.py
easy_tenants/utils.py
easy_tenants/management/__init__.py
easy_tenants/management/commands/__init__.py
easy_tenants/management/commands/shell_tenant.py
django_easy_tenants-0.9.5.dist-info/METADATA
django_easy_tenants-0.9.5.dist-info/WHEEL
django_easy_tenants-0.9.5.dist-info/top_level.txt
django_easy_tenants-0.9.5.dist-info/RECORD
