Metadata-Version: 2.4
Name: django-easy-tenants
Version: 0.9.5
Summary: Easy to create applications that use tenants in django
Author-email: Cleiton Lima <cleiton.limapin@gmail.com>
License-Expression: MIT
Project-URL: Repository, https://github.com/CleitonDeLima/django-easy-tenants
Project-URL: Homepage, https://github.com/CleitonDeLima/django-easy-tenants
Classifier: Development Status :: 5 - Production/Stable
Classifier: Framework :: Django :: 4.2
Classifier: Framework :: Django :: 5.0
Classifier: Framework :: Django :: 5.1
Classifier: Framework :: Django :: 5.2
Classifier: Intended Audience :: Developers
Classifier: Natural Language :: English
Classifier: Operating System :: OS Independent
Classifier: Programming Language :: Python :: 3 :: Only
Classifier: Programming Language :: Python :: 3.9
Classifier: Programming Language :: Python :: 3.10
Classifier: Programming Language :: Python :: 3.11
Classifier: Programming Language :: Python :: 3.12
Classifier: Programming Language :: Python :: Implementation :: CPython
Requires-Python: >=3.9
License-File: LICENSE
License-File: AUTHORS
Requires-Dist: django>=4.2
Dynamic: license-file
